pyeikonal/__init__.py
pyeikonal/eikonal/__init__.py
pyeikonal/eikonal/eikonal2d.py
pyeikonal/eikonal/eikonal3d.py
pyeikonal/eikonal/utils.py
pyeikonal/model/__init__.py
pyeikonal/model/model2d.py
pyeikonal/model/model3d.py
pyeikonal/model/rbf.py
pyeikonal/model/utils.py
pyeikonal/problem/__init__.py
pyeikonal/problem/problem2d.py
pyeikonal/problem/problem3d.py
pyeikonal/problem/utils.py
pyeikonal/solver/__init__.py
pyeikonal/solver/recorder.py
pyeikonal/utils/__init__.py
pyeikonal/utils/lcurve.py
pyeikonal/utils/utils.py
pyeikonal/viz/__init__.py
pyeikonal/viz/plot.py
pyeikonal-0.0.5.dist-info/LICENSE
pyeikonal-0.0.5.dist-info/METADATA
pyeikonal-0.0.5.dist-info/WHEEL
pyeikonal-0.0.5.dist-info/RECORD
